Workbook
Name BW_Verbindung: Hinweise!$B$1

Sheet Cockpit
B1: Management Cockpit
B2: ="Geschäftsjahr "&C4&" · "&C3
B3: Unternehmen | C3: Apple Inc. | J3: =CUBEMEMBER(BW_Verbindung,"[dim_company].[company_id].&["&$C$5&"]",$C$3)
B4: Geschäftsjahr | C4: =YEAR(TODAY())-1 | J4: =CUBEMEMBER(BW_Verbindung,"[dim_period].[fiscal_year].&["&$C$4&"]","GJ "&$C$4)
B5: Unternehmens-ID | C5: =_xlfn.XLOOKUP($C$3,Stammdaten!$A:$A,Stammdaten!$B:$B,"nicht gefunden") | J5: =CUBEMEMBER(BW_Verbindung,"[dim_period].[fiscal_year].&["&($C$4-1)&"]","GJ "&($C$4-1))
B6: LEI | C6: =_xlfn.XLOOKUP($C$3,Stammdaten!$A:$A,Stammdaten!$C:$C,"nicht gefunden") | J6: =CUBEMEMBER(BW_Verbindung,"[dim_period].[is_fiscal_year_end].&[1]","Geschäftsjahresende")
B7: CIK | C7: =_xlfn.XLOOKUP($C$3,Stammdaten!$A:$A,Stammdaten!$D:$D,"nicht gefunden") | J7: =CUBEMEMBER(BW_Verbindung,"[dim_scenario].[scenario_code].&[PLAN]","Plan")
B8: Sektor | C8: =_xlfn.XLOOKUP($C$3,Stammdaten!$A:$A,Stammdaten!$E:$E,"nicht gefunden") | J8: =CUBEMEMBER(BW_Verbindung,"[dim_scenario].[scenario_code].&[IST]","Ist")
B9: Land | C9: =_xlfn.XLOOKUP($C$3,Stammdaten!$A:$A,Stammdaten!$F:$F,"nicht gefunden")
B10: Status | C10: =_xlfn.XLOOKUP($C$3,Stammdaten!$A:$A,Stammdaten!$H:$H,"nicht gefunden")
B12: Größen in Mio. EUR
B13: Position | C13: GJ | D13: Vorjahr | E13: Δ % | F13: Plan GJ | G13: Plan-Ist %
B14: Umsatz | C14: =IFERROR(CUBEVALUE(BW_Verbindung,"[Measures].[Umsatz]",$J$3,$J$4,$J$8)/10^6,"–") | D14: =IFERROR(CUBEVALUE(BW_Verbindung,"[Measures].[Umsatz]",$J$3,$J$5,$J$8)/10^6,"–") | E14: =IF(AND(ISNUMBER(C14),ISNUMBER(D14),D14<>0),(C14-D14)/ABS(D14),"–") | F14: =IFERROR(CUBEVALUE(BW_Verbindung,"[Measures].[Umsatz]",$J$3,$J$4,$J$7)/10^6,"–") | G14: =IF(AND(ISNUMBER(C14),ISNUMBER(F14),F14<>0),(C14-F14)/ABS(F14),"–")
B15: EBIT | C15: =IFERROR(CUBEVALUE(BW_Verbindung,"[Measures].[EBIT]",$J$3,$J$4,$J$8)/10^6,"–") | D15: =IFERROR(CUBEVALUE(BW_Verbindung,"[Measures].[EBIT]",$J$3,$J$5,$J$8)/10^6,"–") | E15: =IF(AND(ISNUMBER(C15),ISNUMBER(D15),D15<>0),(C15-D15)/ABS(D15),"–")
B16: Jahresergebnis | C16: =IFERROR(CUBEVALUE(BW_Verbindung,"[Measures].[Jahresergebnis]",$J$3,$J$4,$J$8)/10^6,"–") | D16: =IFERROR(CUBEVALUE(BW_Verbindung,"[Measures].[Jahresergebnis]",$J$3,$J$5,$J$8)/10^6,"–") | E16: =IF(AND(ISNUMBER(C16),ISNUMBER(D16),D16<>0),(C16-D16)/ABS(D16),"–")
B17: Operativer Cashflow | C17: =IFERROR(CUBEVALUE(BW_Verbindung,"[Measures].[Operativer Cashflow]",$J$3,$J$4,$J$8)/10^6,"–") | D17: =IFERROR(CUBEVALUE(BW_Verbindung,"[Measures].[Operativer Cashflow]",$J$3,$J$5,$J$8)/10^6,"–") | E17: =IF(AND(ISNUMBER(C17),ISNUMBER(D17),D17<>0),(C17-D17)/ABS(D17),"–")
B18: Bilanzsumme | C18: =IFERROR(CUBEVALUE(BW_Verbindung,"[Measures].[Bilanzsumme]",$J$3,$J$4,$J$8)/10^6,"–") | D18: =IFERROR(CUBEVALUE(BW_Verbindung,"[Measures].[Bilanzsumme]",$J$3,$J$5,$J$8)/10^6,"–") | E18: =IF(AND(ISNUMBER(C18),ISNUMBER(D18),D18<>0),(C18-D18)/ABS(D18),"–")
B19: Eigenkapital | C19: =IFERROR(CUBEVALUE(BW_Verbindung,"[Measures].[Eigenkapital]",$J$3,$J$4,$J$8)/10^6,"–") | D19: =IFERROR(CUBEVALUE(BW_Verbindung,"[Measures].[Eigenkapital]",$J$3,$J$5,$J$8)/10^6,"–") | E19: =IF(AND(ISNUMBER(C19),ISNUMBER(D19),D19<>0),(C19-D19)/ABS(D19),"–")
B20: Liquide Mittel | C20: =IFERROR(CUBEVALUE(BW_Verbindung,"[Measures].[Liquide Mittel]",$J$3,$J$4,$J$8)/10^6,"–") | D20: =IFERROR(CUBEVALUE(BW_Verbindung,"[Measures].[Liquide Mittel]",$J$3,$J$5,$J$8)/10^6,"–") | E20: =IF(AND(ISNUMBER(C20),ISNUMBER(D20),D20<>0),(C20-D20)/ABS(D20),"–")
B22: Kennzahlen zum Geschäftsjahresende
B23: Kennzahl | C23: GJ | D23: Vorjahr | E23: Δ | F23: Sektorperzentil | G23: Rote Flagge
B24: Eigenkapitalquote | C24: =IFERROR(CUBEVALUE(BW_Verbindung,"[Measures].[KPI Wert]",$J$3,$J$4,$J$6,$K24),"–") | D24: =IFERROR(CUBEVALUE(BW_Verbindung,"[Measures].[KPI Wert]",$J$3,$J$5,$J$6,$K24),"–") | E24: =IF(AND(ISNUMBER(C24),ISNUMBER(D24)),C24-D24,"–") | F24: =IFERROR(CUBEVALUE(BW_Verbindung,"[Measures].[Sektorperzentil]",$J$3,$J$4,$J$6,$K24),"–") | G24: =IFERROR(IF(CUBEVALUE(BW_Verbindung,"[Measures].[Rote Flaggen]",$J$3,$J$4,$J$6,$K24)>0,"rot",""),"") | K24: =CUBEMEMBER(BW_Verbindung,"[dim_kpi].[kpi_code].&[EQUITY_RATIO]","Eigenkapitalquote")
B25: EBIT-Marge | C25: =IFERROR(CUBEVALUE(BW_Verbindung,"[Measures].[KPI Wert]",$J$3,$J$4,$J$6,$K25),"–") | D25: =IFERROR(CUBEVALUE(BW_Verbindung,"[Measures].[KPI Wert]",$J$3,$J$5,$J$6,$K25),"–") | E25: =IF(AND(ISNUMBER(C25),ISNUMBER(D25)),C25-D25,"–") | F25: =IFERROR(CUBEVALUE(BW_Verbindung,"[Measures].[Sektorperzentil]",$J$3,$J$4,$J$6,$K25),"–") | G25: =IFERROR(IF(CUBEVALUE(BW_Verbindung,"[Measures].[Rote Flaggen]",$J$3,$J$4,$J$6,$K25)>0,"rot",""),"") | K25: =CUBEMEMBER(BW_Verbindung,"[dim_kpi].[kpi_code].&[EBIT_MARGIN]","EBIT-Marge")
B26: Bruttomarge | C26: =IFERROR(CUBEVALUE(BW_Verbindung,"[Measures].[KPI Wert]",$J$3,$J$4,$J$6,$K26),"–") | D26: =IFERROR(CUBEVALUE(BW_Verbindung,"[Measures].[KPI Wert]",$J$3,$J$5,$J$6,$K26),"–") | E26: =IF(AND(ISNUMBER(C26),ISNUMBER(D26)),C26-D26,"–") | F26: =IFERROR(CUBEVALUE(BW_Verbindung,"[Measures].[Sektorperzentil]",$J$3,$J$4,$J$6,$K26),"–") | G26: =IFERROR(IF(CUBEVALUE(BW_Verbindung,"[Measures].[Rote Flaggen]",$J$3,$J$4,$J$6,$K26)>0,"rot",""),"") | K26: =CUBEMEMBER(BW_Verbindung,"[dim_kpi].[kpi_code].&[GROSS_MARGIN]","Bruttomarge")
B27: Days Sales Outstanding | C27: =IFERROR(CUBEVALUE(BW_Verbindung,"[Measures].[KPI Wert]",$J$3,$J$4,$J$6,$K27),"–") | D27: =IFERROR(CUBEVALUE(BW_Verbindung,"[Measures].[KPI Wert]",$J$3,$J$5,$J$6,$K27),"–") | E27: =IF(AND(ISNUMBER(C27),ISNUMBER(D27)),C27-D27,"–") | F27: =IFERROR(CUBEVALUE(BW_Verbindung,"[Measures].[Sektorperzentil]",$J$3,$J$4,$J$6,$K27),"–") | G27: =IFERROR(IF(CUBEVALUE(BW_Verbindung,"[Measures].[Rote Flaggen]",$J$3,$J$4,$J$6,$K27)>0,"rot",""),"") | K27: =CUBEMEMBER(BW_Verbindung,"[dim_kpi].[kpi_code].&[DSO]","Days Sales Outstanding")
B28: Days Inventory Outstanding | C28: =IFERROR(CUBEVALUE(BW_Verbindung,"[Measures].[KPI Wert]",$J$3,$J$4,$J$6,$K28),"–") | D28: =IFERROR(CUBEVALUE(BW_Verbindung,"[Measures].[KPI Wert]",$J$3,$J$5,$J$6,$K28),"–") | E28: =IF(AND(ISNUMBER(C28),ISNUMBER(D28)),C28-D28,"–") | F28: =IFERROR(CUBEVALUE(BW_Verbindung,"[Measures].[Sektorperzentil]",$J$3,$J$4,$J$6,$K28),"–") | G28: =IFERROR(IF(CUBEVALUE(BW_Verbindung,"[Measures].[Rote Flaggen]",$J$3,$J$4,$J$6,$K28)>0,"rot",""),"") | K28: =CUBEMEMBER(BW_Verbindung,"[dim_kpi].[kpi_code].&[DIO]","Days Inventory Outstanding")
B29: Days Payables Outstanding | C29: =IFERROR(CUBEVALUE(BW_Verbindung,"[Measures].[KPI Wert]",$J$3,$J$4,$J$6,$K29),"–") | D29: =IFERROR(CUBEVALUE(BW_Verbindung,"[Measures].[KPI Wert]",$J$3,$J$5,$J$6,$K29),"–") | E29: =IF(AND(ISNUMBER(C29),ISNUMBER(D29)),C29-D29,"–") | F29: =IFERROR(CUBEVALUE(BW_Verbindung,"[Measures].[Sektorperzentil]",$J$3,$J$4,$J$6,$K29),"–") | G29: =IFERROR(IF(CUBEVALUE(BW_Verbindung,"[Measures].[Rote Flaggen]",$J$3,$J$4,$J$6,$K29)>0,"rot",""),"") | K29: =CUBEMEMBER(BW_Verbindung,"[dim_kpi].[kpi_code].&[DPO]","Days Payables Outstanding")
B30: Cash Conversion Cycle | C30: =IFERROR(CUBEVALUE(BW_Verbindung,"[Measures].[KPI Wert]",$J$3,$J$4,$J$6,$K30),"–") | D30: =IFERROR(CUBEVALUE(BW_Verbindung,"[Measures].[KPI Wert]",$J$3,$J$5,$J$6,$K30),"–") | E30: =IF(AND(ISNUMBER(C30),ISNUMBER(D30)),C30-D30,"–") | F30: =IFERROR(CUBEVALUE(BW_Verbindung,"[Measures].[Sektorperzentil]",$J$3,$J$4,$J$6,$K30),"–") | G30: =IFERROR(IF(CUBEVALUE(BW_Verbindung,"[Measures].[Rote Flaggen]",$J$3,$J$4,$J$6,$K30)>0,"rot",""),"") | K30: =CUBEMEMBER(BW_Verbindung,"[dim_kpi].[kpi_code].&[CCC]","Cash Conversion Cycle")
B31: Liquidität 3. Grades | C31: =IFERROR(CUBEVALUE(BW_Verbindung,"[Measures].[KPI Wert]",$J$3,$J$4,$J$6,$K31),"–") | D31: =IFERROR(CUBEVALUE(BW_Verbindung,"[Measures].[KPI Wert]",$J$3,$J$5,$J$6,$K31),"–") | E31: =IF(AND(ISNUMBER(C31),ISNUMBER(D31)),C31-D31,"–") | F31: =IFERROR(CUBEVALUE(BW_Verbindung,"[Measures].[Sektorperzentil]",$J$3,$J$4,$J$6,$K31),"–") | G31: =IFERROR(IF(CUBEVALUE(BW_Verbindung,"[Measures].[Rote Flaggen]",$J$3,$J$4,$J$6,$K31)>0,"rot",""),"") | K31: =CUBEMEMBER(BW_Verbindung,"[dim_kpi].[kpi_code].&[CURRENT_RATIO]","Liquidität 3. Grades")
B32: Nettoverschuldung / EBITDA | C32: =IFERROR(CUBEVALUE(BW_Verbindung,"[Measures].[KPI Wert]",$J$3,$J$4,$J$6,$K32),"–") | D32: =IFERROR(CUBEVALUE(BW_Verbindung,"[Measures].[KPI Wert]",$J$3,$J$5,$J$6,$K32),"–") | E32: =IF(AND(ISNUMBER(C32),ISNUMBER(D32)),C32-D32,"–") | F32: =IFERROR(CUBEVALUE(BW_Verbindung,"[Measures].[Sektorperzentil]",$J$3,$J$4,$J$6,$K32),"–") | G32: =IFERROR(IF(CUBEVALUE(BW_Verbindung,"[Measures].[Rote Flaggen]",$J$3,$J$4,$J$6,$K32)>0,"rot",""),"") | K32: =CUBEMEMBER(BW_Verbindung,"[dim_kpi].[kpi_code].&[DEBT_EBITDA]","Nettoverschuldung / EBITDA")
B33: Altman Z'' (1995) | C33: =IFERROR(CUBEVALUE(BW_Verbindung,"[Measures].[KPI Wert]",$J$3,$J$4,$J$6,$K33),"–") | D33: =IFERROR(CUBEVALUE(BW_Verbindung,"[Measures].[KPI Wert]",$J$3,$J$5,$J$6,$K33),"–") | E33: =IF(AND(ISNUMBER(C33),ISNUMBER(D33)),C33-D33,"–") | F33: =IFERROR(CUBEVALUE(BW_Verbindung,"[Measures].[Sektorperzentil]",$J$3,$J$4,$J$6,$K33),"–") | G33: =IFERROR(IF(CUBEVALUE(BW_Verbindung,"[Measures].[Rote Flaggen]",$J$3,$J$4,$J$6,$K33)>0,"rot",""),"") | K33: =CUBEMEMBER(BW_Verbindung,"[dim_kpi].[kpi_code].&[ZPP]","Altman Z'' (1995)")
B35: Frühwarnung
B36: Kennzahl | C36: Wert
B37: Insolvenzwahrscheinlichkeit 12 Monate | C37: =IFERROR(CUBEVALUE(BW_Verbindung,"[Measures].[Risiko 12M]",$J$3),"–")
B38: Veränderung zum Vorquartal | C38: =IFERROR(CUBEVALUE(BW_Verbindung,"[Measures].[Risiko Veränderung zum Vorquartal]",$J$3),"–")
B39: Altman Z'' (letzte Periode) | C39: =IFERROR(CUBEVALUE(BW_Verbindung,"[Measures].[Z'' Score]",$J$3),"–")
B40: Cash-Potenzial in Mio. EUR | C40: =IFERROR(CUBEVALUE(BW_Verbindung,"[Measures].[Cash-Potenzial]",$J$3,$J$4)/10^6,"–")
B42: Datenstand | C42: =IFERROR(CUBEVALUE(BW_Verbindung,"[Measures].[Datenstand]"),"–")
B43: Quelle: SEC EDGAR, ESEF (filings.xbrl.org), GLEIF, EZB · Modell: Bilanzwerk (Power BI)
B44: Risikobänder: rot ab 10 %, gelb ab 3 % (ADR-007). Δ % gegen Vorjahr; Plan nur für Umsatz.

Sheet Stammdaten
A1: company_name | B1: company_id | C1: lei | D1: cik | E1: sector_de | F1: country_code | G1: hq_city | H1: company_status | I1: match_source | K1: Golden Record (aktuelle Version), geladen per Power Query aus marts.dim_company.

Sheet Risikoliste
A1: company_name | B1: sector_de | C1: as_of_date | D1: probability_12m | E1: risk_band | F1: top_3_drivers | H1: Risikoliste Champion-Modell, letzter Stichtag, geladen per Power Query.

Sheet Peer
A1: Peer-Vergleich
A2: PivotTable auf dem Semantikmodell mit Datenschnitten für Sektor und Geschäftsjahr; wird von finalize_workbook.ps1 ab Zelle A4 angelegt.

Sheet Hinweise
A1: Verbindung | B1: Bilanzwerk
A2: Zweck | B2: Monatsbericht für Controlling: ein Blatt Cockpit mit festem Layout (CUBE-Formeln).
A3: Aktualisieren | B3: Makro RefreshAndExport (Modul modRefreshAndExport): aktualisiert alle Verbindungen und speichert das Cockpit als PDF mit Datum im Ordner Export.
A4: Unternehmen wählen | B4: Cockpit!C3 (Liste aus Stammdaten). Die ID in C5 kommt per XVERWEIS aus dem Golden Record.
A5: Kennzahlen | B5: Definitionen, Einheiten und Schwellen: dim_kpi im Modell, Quelle dbt/seeds/kpi_definitions.csv.
A6: Versionen | B6: Werte nach Restatements (latest). Das Frühwarnmodell nutzt die Erstveröffentlichung.
